CyzHub/CyzHub.py
CyzHub/CyzHub_1.0.4.py
CyzHub/__init__.py
CyzHub-1.1.4.dist-info/LICENSE
CyzHub-1.1.4.dist-info/METADATA
CyzHub-1.1.4.dist-info/WHEEL
CyzHub-1.1.4.dist-info/top_level.txt
CyzHub-1.1.4.dist-info/RECORD
