Metadata-Version: 2.1
Name: CyzHub
Version: 1.1.4
Summary: 深度学习的一些工具（基础阶段的，供参考学习使用）这个版本增加了把我们的tensor以图象的形式显示，包括数值是在[0,1]和[0,255]
Home-page: https://github.com/CyzSpace/CyzHub
Author: 陈颍州
Author-email: cyzroot@outlook.com
Classifier: Programming Language :: Python :: 3
Classifier: License :: OSI Approved :: MIT License
Classifier: Operating System :: OS Independent
Requires-Python: >=3.6
License-File: LICENSE
